[
    {
        "name": "Alyanna Magpantay",
        "contact": "09123432122",
        "date": "2025-05-08",
        "city": "Batangas City",
        "resort": "Luks Lofts Hotel",
        "resort_desc": "A modern luxury hotel with smart rooms and a private pool per suite.",
        "resort_price": "â‚±15,000 - â‚±30,000 per night"
    },
    {
        "name": "John Paulo M. Roque",
        "contact": "09888888888",
        "date": "2025-05-22",
        "city": "Lipa",
        "resort": "The Farm at San Benito",
        "resort_desc": "A luxury wellness resort offering health retreats and eco-luxury villas.",
        "resort_price": "â‚±10,000 - â‚±50,000 per night"
    },
    {
        "name": "alyanna",
        "contact": "00969777345",
        "date": "2025-05-22",
        "city": "Batangas City",
        "resort": "PonteFino Hotel",
        "resort_desc": "A stylish business hotel with excellent amenities in Batangas City.",
        "resort_price": "â‚±6,000 - â‚±12,000 per night"
    },
    {
        "name": "Alyanna Magpantay",
        "contact": "00969777345",
        "date": "2025-05-30",
        "city": "Lipa",
        "resort": "The Farm at San Benito",
        "resort_desc": "A luxury wellness resort offering health retreats and eco-luxury villas.",
        "resort_price": "₱10,000 - ₱50,000 per night"
    }
]